grpc_proto_validator/__init__.py
grpc_proto_validator/validator.py
grpc_proto_validator/validator_pb2.py
grpc_proto_validator-0.1.2.dev0.dist-info/LICENSE.txt
grpc_proto_validator-0.1.2.dev0.dist-info/METADATA
grpc_proto_validator-0.1.2.dev0.dist-info/RECORD
grpc_proto_validator-0.1.2.dev0.dist-info/WHEEL
grpc_proto_validator-0.1.2.dev0.dist-info/top_level.txt
