Metadata-Version: 2.1
Name: grpc-proto-validator
Version: 0.1.2.dev0
Summary: grpc proto validator.
Home-page: https://github.com/v1c77/py_grpc_validator
Author: v1c77
Author-email: heyuhuade@gmail.com
License: MIT
Platform: any
Classifier: Development Status :: 2 - Pre-Alpha
Classifier: Intended Audience :: Developers
Classifier: License :: OSI Approved :: MIT License
Classifier: Operating System :: OS Independent
Classifier: Programming Language :: Python :: 2.7
Classifier: Programming Language :: Python :: 3.5
Classifier: Topic :: Software Development :: Pre-processors
Classifier: Topic :: Software Development :: Quality Assurance
Requires-Python: >=2.7, !=3.0.*, !=3.1.*, !=3.2.*, !=3.3.*
Requires-Dist: six (>=1.11.0)
Requires-Dist: grpcio (>=1.11.0)
Requires-Dist: grpcio-tools (>=1.11.0)
Requires-Dist: protobuf (>3.6.0)
